pralab_phys/__init__.py
pralab_phys/py.typed
pralab_phys/analysis/__init__.py
pralab_phys/ezgraph/__init__.py
pralab_phys/ezgraph/ezgraph_2d.py
pralab_phys/ezgraph/ipygraph.py
pralab_phys/ezgraph/realtimeplot.py
pralab_phys/ezgraph/realtimeplot_fixed.py
pralab_phys/eztools/__init__.py
pralab_phys/eztools/openexp.py
pralab_phys/eztools/visa.py
pralab_phys/qcodes_drivers/__init__.py
pralab_phys/qcodes_drivers/keithley2182a.py
pralab_phys/qcodes_drivers/keithley2182a1ch.py
pralab_phys/qcodes_drivers/keithley6221.py
pralab_phys/qcodes_drivers/li5650.py
pralab_phys/qcodes_drivers/qddotnet.py
pralab_phys/qcodes_drivers/qdvisa.py
pralab_phys/qcodes_drivers/yokogawa7651.py
pralab_phys-0.3.9.dist-info/METADATA
pralab_phys-0.3.9.dist-info/WHEEL
pralab_phys-0.3.9.dist-info/top_level.txt
pralab_phys-0.3.9.dist-info/RECORD
