Metadata-Version: 2.4
Name: pralab_phys
Version: 0.3.9
Summary: Add your description here
Requires-Python: >=3.10
Requires-Dist: hvplot>=0.10.0
Requires-Dist: jupyterlab>=4.2.5
Requires-Dist: numpy>=2.1.0
Requires-Dist: pandas>=2.2.1
Requires-Dist: plotly>=5.22.0
Requires-Dist: pyvisa>=1.14.1
Requires-Dist: qcodes>=0.48.0
Requires-Dist: pythonnet>=3.0.3
Requires-Dist: ipywidgets>=8.1.5
Requires-Dist: dash>=3.0.4
